PyMsOfa/PyMsOfa.py
PyMsOfa/PyMsOfa_astrometry.py
PyMsOfa/PyMsOfa_basic.py
PyMsOfa/PyMsOfa_earth_attitude.py
PyMsOfa/PyMsOfa_t.py
PyMsOfa/PyMsOfa_time.py
PyMsOfa/__init__.py
PyMsOfa/libsofa_c.cp39-win_amd64.pyd
PyMsOfa_ctypes-0.0.3.dist-info/LICENSE
PyMsOfa_ctypes-0.0.3.dist-info/METADATA
PyMsOfa_ctypes-0.0.3.dist-info/WHEEL
PyMsOfa_ctypes-0.0.3.dist-info/top_level.txt
PyMsOfa_ctypes-0.0.3.dist-info/RECORD
