Metadata-Version: 2.1
Name: PyMsOfa-ctypes
Version: 0.0.3
Summary: a Python package for the Standards of Fundamental Astronomy (SOFA) service
Author: Ji,jianghui
Author-email: jijh@pmo.ac.cn
License: MIT
Classifier: Development Status :: 5 - Production/Stable
Classifier: Intended Audience :: Developers
Classifier: Programming Language :: Python :: 3.0
Classifier: Operating System :: Unix
Classifier: Operating System :: MacOS
Classifier: Operating System :: Microsoft :: Windows
Classifier: Topic :: Scientific/Engineering :: Astronomy
License-File: LICENSE
